{
  "id": "fd_block_salt_lake",
  "name_en": "FD Block Salt Lake",
  "name_bn": "এফডি ব্লক সল্ট লেক",
  "location_en": "Salt Lake, Kolkata",
  "location_bn": "সল্ট লেক, কলকাতা",
  "address": "",
  "coordinates": [],
  "nearest_metro": "",
  "how_to_reach_en": "",
  "how_to_reach_bn": "",
  "crowd_level": "",
  "best_visiting_time": "",
  "specialty_en": "Dazzling lights and a bedazzling effect in the evening",
  "specialty_bn": "ঝলমলে আলো এবং সন্ধ্যায় চমকপ্রদ প্রভাব",
  "theme_2024": "",
  "established_year": 1984,
  "timings": "",
  "tags": [
    "Durga Puja",
    "Kolkata",
    "Pandal Hoping"
  ]
}